Metadata-Version: 2.1
Name: ansys-api-mapdl-v0
Version: 0.4.1
Summary: Autogenerated python gRPC interface package for ansys-api-mapdl-v0 built on 04:49:37 on 29 October 2021
Home-page: https://github.com/pyansys/
Author: Ansys Inc.
Author-email: support@ansys.com
License: MIT
Platform: UNKNOWN
Requires-Python: >=3.5.*
